VERSION
qbit_manage.py
modules/__init__.py
modules/apprise.py
modules/auth.py
modules/config.py
modules/logs.py
modules/notifiarr.py
modules/qbit_error_handler.py
modules/qbittorrent.py
modules/scheduler.py
modules/torrent_hash_generator.py
modules/util.py
modules/web_api.py
modules/webhooks.py
modules/core/__init__.py
modules/core/category.py
modules/core/recheck.py
modules/core/remove_orphaned.py
modules/core/remove_unregistered.py
modules/core/share_limits.py
modules/core/tag_nohardlinks.py
modules/core/tags.py
qbit_manage-4.6.4.dist-info/licenses/LICENSE
web-ui/README.md
web-ui/index.html
web-ui/css/components.css
web-ui/css/main.css
web-ui/css/responsive.css
web-ui/css/themes.css
web-ui/css/components/_accordion.css
web-ui/css/components/_alert.css
web-ui/css/components/_array-field.css
web-ui/css/components/_badge.css
web-ui/css/components/_buttons.css
web-ui/css/components/_card.css
web-ui/css/components/_close-icon-button.css
web-ui/css/components/_command-panel.css
web-ui/css/components/_complex-object-card.css
web-ui/css/components/_documentation-viewer.css
web-ui/css/components/_dropdown.css
web-ui/css/components/_forms.css
web-ui/css/components/_key-value-list.css
web-ui/css/components/_log-viewer.css
web-ui/css/components/_modal.css
web-ui/css/components/_pagination.css
web-ui/css/components/_scheduler-control.css
web-ui/css/components/_share-limits.css
web-ui/css/components/_skeleton.css
web-ui/css/components/_tabs.css
web-ui/css/components/_toast.css
web-ui/css/components/_toggle-switch.css
web-ui/img/android-chrome-192x192.png
web-ui/img/android-chrome-512x512.png
web-ui/img/apple-touch-icon.png
web-ui/img/favicon-16x16.png
web-ui/img/favicon-32x32.png
web-ui/img/favicon.ico
web-ui/img/qbm_logo.png
web-ui/img/site.webmanifest
web-ui/js/api.js
web-ui/js/app.js
web-ui/js/components/SchedulerControl.js
web-ui/js/components/command-panel.js
web-ui/js/components/config-form.js
web-ui/js/components/documentation-viewer.js
web-ui/js/components/header.js
web-ui/js/components/log-viewer.js
qbit_manage-4.6.4.dist-info/METADATA
qbit_manage-4.6.4.dist-info/WHEEL
qbit_manage-4.6.4.dist-info/entry_points.txt
qbit_manage-4.6.4.dist-info/top_level.txt
qbit_manage-4.6.4.dist-info/RECORD
