Metadata-Version: 2.4
Name: qbit_manage
Version: 4.6.4
Summary: This tool will help manage tedious tasks in qBittorrent and automate them. Tag, categorize, remove Orphaned data, remove unregistered torrents and much much more.
Home-page: https://github.com/StuffAnThings
Download-URL: https://github.com/StuffAnThings/qbit_manage
Author: bobokun
Author-email: 
License-Expression: MIT
Project-URL: Homepage, https://github.com/StuffAnThings
Project-URL: Repository, https://github.com/StuffAnThings/qbit_manage
Requires-Python: >=3.9
License-File: LICENSE
Requires-Dist: argon2-cffi==25.1.0
Requires-Dist: bencodepy==0.9.5
Requires-Dist: croniter==6.0.0
Requires-Dist: fastapi==0.121.2
Requires-Dist: GitPython==3.1.45
Requires-Dist: humanize==4.13.0
Requires-Dist: pytimeparse2==1.7.1
Requires-Dist: qbittorrent-api==2025.11.0
Requires-Dist: requests==2.32.5
Requires-Dist: retrying==1.4.2
Requires-Dist: ruamel.yaml==0.18.16
Requires-Dist: slowapi==0.1.9
Requires-Dist: uvicorn==0.38.0
Provides-Extra: dev
Requires-Dist: pre-commit==4.3.0; extra == "dev"
Requires-Dist: ruff==0.14.5; extra == "dev"
Dynamic: download-url
Dynamic: home-page
Dynamic: license-file
